setup.py
apostle/__init__.py
apostle/exceptions.py
apostle/mail.py
apostle/queue.py
apostle.egg-info/PKG-INFO
apostle.egg-info/SOURCES.txt
apostle.egg-info/dependency_links.txt
apostle.egg-info/requires.txt
apostle.egg-info/top_level.txt