Metadata-Version: 1.1
Name: apostle
Version: 0.1.0
Summary: Python Bindings for Apostle.io
Home-page: http://apostle.io
Author: Mal Curtis
Author-email: mal@apostle.io
License: Copyright (C) 2013 Apostle.io
